quicklog/__init__.py
quicklog/__main__.py
donjon_quicklog-1.0.2.post1.dist-info/COPYING
donjon_quicklog-1.0.2.post1.dist-info/COPYING.LESSER
donjon_quicklog-1.0.2.post1.dist-info/METADATA
donjon_quicklog-1.0.2.post1.dist-info/WHEEL
donjon_quicklog-1.0.2.post1.dist-info/entry_points.txt
donjon_quicklog-1.0.2.post1.dist-info/RECORD
