Metadata-Version: 2.3
Name: donjon-quicklog
Version: 1.0.2.post1
Summary: Python3 library for logging experimental results
License: LGPL-3.0-or-later
Author: Olivier Hériveaux
Author-email: olivier.heriveaux@ledger.fr
Requires-Python: >=3.9,<4
Classifier: License :: OSI Approved :: GNU Lesser General Public License v3 or later (LGPLv3+)
Classifier: Programming Language :: Python :: 3
Classifier: Programming Language :: Python :: 3.9
Classifier: Programming Language :: Python :: 3.10
Classifier: Programming Language :: Python :: 3.11
Classifier: Programming Language :: Python :: 3.12
Classifier: Programming Language :: Python :: 3.13
Requires-Dist: click
Requires-Dist: numpy
Requires-Dist: progressbar
